rizpass/.gitignore
rizpass/__init__.py
rizpass/__main__.py
rizpass/better_input.py
rizpass/cred_manager.py
rizpass/credentials.py
rizpass/database_manager.py
rizpass/file_manager.py
rizpass/misc.py
rizpass/output.py
rizpass/passwords.py
rizpass/requirements.txt
rizpass/rizpass.py
rizpass/setup_rizpass.py
rizpass/test_better_input.py
rizpass/test_credentials.py
rizpass/test_file_manager.py
rizpass/test_passwords.py
rizpass/test_validator.py
rizpass/tests.py
rizpass/user_functions.py
rizpass/validator.py
rizpass-0.0.5.dist-info/METADATA
rizpass-0.0.5.dist-info/WHEEL
rizpass-0.0.5.dist-info/licenses/LICENSE
rizpass-0.0.5.dist-info/RECORD
