Metadata-Version: 2.1
Name: rizpass
Version: 0.0.5
Summary: A simple and opensource password manager
Project-URL: Homepage, https://github.com/rizwanmustafa/Rizpass
Project-URL: Bug Tracker, https://github.com/rizwanmustafa/Rizpass/issues
Author-email: Rizwan Mustafa <rizwanmustafa0000@gmail.com>
License-File: LICENSE
Classifier: License :: OSI Approved :: GNU Affero General Public License v3 or later (AGPLv3+)
Classifier: Operating System :: OS Independent
Classifier: Programming Language :: Python :: 3
Requires-Python: >=3.8
Requires-Dist: colorama
Requires-Dist: cryptography
Requires-Dist: pymongo[srv]
Requires-Dist: pymysql
Requires-Dist: pyperclip
